pyUSPTO/__init__.py
pyUSPTO/config.py
pyUSPTO/exceptions.py
pyUSPTO/http_config.py
pyUSPTO/py.typed
pyUSPTO/warnings.py
pyUSPTO/clients/__init__.py
pyUSPTO/clients/base.py
pyUSPTO/clients/bulk_data.py
pyUSPTO/clients/patent_data.py
pyUSPTO/clients/petition_decisions.py
pyUSPTO/clients/ptab_appeals.py
pyUSPTO/clients/ptab_interferences.py
pyUSPTO/clients/ptab_trials.py
pyUSPTO/models/__init__.py
pyUSPTO/models/base.py
pyUSPTO/models/bulk_data.py
pyUSPTO/models/patent_data.py
pyUSPTO/models/petition_decisions.py
pyUSPTO/models/ptab.py
pyUSPTO/models/utils.py
pyUSPTO/utils/__init__.py
pyUSPTO/utils/http.py
pyuspto-0.3.2.dist-info/licenses/LICENSE
pyuspto-0.3.2.dist-info/METADATA
pyuspto-0.3.2.dist-info/WHEEL
pyuspto-0.3.2.dist-info/top_level.txt
pyuspto-0.3.2.dist-info/zip-safe
pyuspto-0.3.2.dist-info/RECORD
