Metadata-Version: 2.4
Name: pyUSPTO
Version: 0.3.2
Summary: A Modern Python client for accessing United Stated Patent and Trademark Office (USPTO) Open Data Portal (ODP) APIs.
Author-email: Andrew Piechocki <apiechocki@dunlapcodding.com>
License-Expression: MIT
Project-URL: GitHub, https://github.com/DunlapCoddingPC/pyUSPTO
Project-URL: issues, https://github.com/DunlapCoddingPC/pyUSPTO/issues
Project-URL: Documentation, https://pyuspto.readthedocs.io/en/latest/
Keywords: uspto,patent,odp,client,bulk data,patent data
Classifier: Programming Language :: Python :: 3
Classifier: Programming Language :: Python :: 3.10
Classifier: Programming Language :: Python :: 3.11
Classifier: Programming Language :: Python :: 3.12
Classifier: Programming Language :: Python :: 3.13
Classifier: Programming Language :: Python :: 3.14
Classifier: Operating System :: OS Independent
Classifier: Development Status :: 4 - Beta
Classifier: Environment :: Console
Classifier: Intended Audience :: Developers
Classifier: Intended Audience :: Education
Classifier: Intended Audience :: Information Technology
Classifier: Intended Audience :: Legal Industry
Classifier: Intended Audience :: Science/Research
Classifier: Intended Audience :: Other Audience
Classifier: Natural Language :: English
Classifier: Operating System :: MacOS
Classifier: Operating System :: POSIX :: Linux
Classifier: Topic :: Software Development :: Libraries
Classifier: Topic :: Scientific/Engineering
Classifier: Topic :: Scientific/Engineering :: Information Analysis
Classifier: Topic :: Education
Classifier: Topic :: Internet :: WWW/HTTP
Classifier: Topic :: Office/Business
Classifier: Topic :: Scientific/Engineering :: Interface Engine/Protocol Translator
Classifier: Topic :: Software Development :: Libraries :: Python Modules
Classifier: Topic :: Utilities
Requires-Python: >=3.10
License-File: LICENSE
Requires-Dist: requests>=2.32.5
Requires-Dist: typing-extensions>=4.15.0; python_version < "3.11"
Requires-Dist: tzdata>=2025.2
Provides-Extra: dev
Requires-Dist: pytest>=9.0.2; extra == "dev"
Requires-Dist: pytest-cov>=7.0.0; extra == "dev"
Requires-Dist: pytest-mock>=3.15.1; extra == "dev"
Requires-Dist: sphinx==8.1.3; extra == "dev"
Requires-Dist: sphinx-rtd-theme>=3.0.0; extra == "dev"
Requires-Dist: sphinx_immaterial>=0.13.8; extra == "dev"
Requires-Dist: sphinx-autodoc-typehints==3.0.1; extra == "dev"
Requires-Dist: sphinx-copybutton>=0.5.2; extra == "dev"
Requires-Dist: myst-parser>=4.0.1; extra == "dev"
Requires-Dist: mypy>=1.19.0; extra == "dev"
Requires-Dist: types-requests>=2.32.4; extra == "dev"
Requires-Dist: ruff>=0.8.0; extra == "dev"
Dynamic: license-file
